drf_scaffold/__init__.py
drf_scaffold/constants.py
drf_scaffold/conf/__init__.py
drf_scaffold/conf/drf_app_template/__init__.py-tpl
drf_scaffold/conf/drf_app_template/admin.py-tpl
drf_scaffold/conf/drf_app_template/apps.py-tpl
drf_scaffold/conf/drf_app_template/models.py-tpl
drf_scaffold/conf/drf_app_template/serializers.py-tpl
drf_scaffold/conf/drf_app_template/tests.py-tpl
drf_scaffold/conf/drf_app_template/urls.py-tpl
drf_scaffold/conf/drf_app_template/views.py-tpl
drf_scaffold/conf/drf_app_template/migrations/__init__.py-tpl
drf_scaffold/management/__init__.py
drf_scaffold/management/commands/__init__.py
drf_scaffold/management/commands/startdrfapp.py
drf_scaffold-0.1.4.dist-info/METADATA
drf_scaffold-0.1.4.dist-info/RECORD
drf_scaffold-0.1.4.dist-info/WHEEL
drf_scaffold-0.1.4.dist-info/top_level.txt
tests/__init__.py
tests/tests_command.py
